{
    "message": "Warning !!!!!!!!!!!!!!!!!!!!!!!!",

    "warningMessage": {
        "message": "Warning !!!!!!!!!!!!!!!!!!!!!!!!"
    },

    "contactList": [
        {
            "name": "first",
            "phoneNumber": 1234567
        },
        {
            "name": "first",
            "phoneNumber": 1234567
        }

    ],
    "gagag": {
        "sdasda": "gagaga"
    },

    "Alerts": [
        {
            "id": 1,
            "name": "1111",
            "latitude": "-33.852",
            "longitude": "151.212"
        },
        {
            "id": 2,
            "name": "122222",
            "latitude": "-33.852",
            "longitude": "151.211"
        },
        {
            "id": 3,
            "name": "333333",
            "latitude": "-33.853",
            "longitude": "151.211"
        }

    ]



}